circheck/__init__.py
circheck/cli.py
circheck/core.py
circheck/astgen/ASTGeneration.py
circheck/astgen/__init__.py
circheck/cdggen/CDGGeneration.py
circheck/cdggen/__init__.py
circheck/detect/Detect.py
circheck/detect/__init__.py
circheck/parser/__init__.py
circheck/target/CircomLexer.py
circheck/target/CircomParser.py
circheck/target/CircomVisitor.py
circheck/target/__init__.py
circheck/typecheck/StaticCheck.py
circheck/typecheck/__init__.py
circheck/utils/AST.py
circheck/utils/CDG.py
circheck/utils/Errors.py
circheck/utils/Report.py
circheck/utils/Visitor.py
circheck/utils/__init__.py
circheck-0.3.0.dist-info/licenses/LICENSE
circheck-0.3.0.dist-info/METADATA
circheck-0.3.0.dist-info/WHEEL
circheck-0.3.0.dist-info/entry_points.txt
circheck-0.3.0.dist-info/top_level.txt
circheck-0.3.0.dist-info/RECORD
