Metadata-Version: 2.4
Name: circheck
Version: 0.3.0
Summary: Static analysis tool to detect ZKP vulnerabilities in Circom circuits.
Author: Dang Duong Minh Nhat
Author-email: dangduongminhnhat2003@gmail.com
License-File: LICENSE
Requires-Dist: antlr4-python3-runtime==4.9.2
Requires-Dist: colorama==0.4.6
Requires-Dist: tqdm==4.67.1
Dynamic: author
Dynamic: author-email
Dynamic: description
Dynamic: description-content-type
Dynamic: license-file
Dynamic: requires-dist
Dynamic: summary
